forest_gen/__init__.py
forest_gen/scene.py
forest_gen/assets/__init__.py
forest_gen/assets/files.py
forest_gen-0.3.8.dist-info/licenses/LICENSE
forest_gen_utils/__init__.py
forest_gen_utils/traversability.py
forest_gen_utils/asset_dist/__init__.py
forest_gen_utils/asset_dist/definitions.py
forest_gen_utils/asset_dist/distribution_builder.py
forest_gen_utils/asset_dist/distribution_config.py
forest_gen_utils/asset_dist/distribution_generator.py
forest_gen_utils/asset_dist/grass.py
forest_gen_utils/asset_dist/sim.py
forest_gen_utils/asset_dist/state.py
forest_gen_utils/asset_dist/terrain_viability.py
forest_gen_utils/asset_dist/understory.py
forest_gen_utils/export/__init__.py
forest_gen_utils/export/export_factory.py
forest_gen_utils/export/export_strategy.py
forest_gen_utils/export/glb_exporter.py
forest_gen_utils/export/png_exporter.py
forest_gen_utils/forest/__init__.py
forest_gen_utils/forest/forest_builder.py
forest_gen_utils/forest/forest_config.py
forest_gen_utils/forest/forest_generator.py
forest_gen_utils/obstacles/__init__.py
forest_gen_utils/obstacles/obstacle.py
forest_gen_utils/obstacles/obstacle_builder.py
forest_gen_utils/obstacles/obstacle_config.py
forest_gen_utils/obstacles/obstacle_generator.py
forest_gen_utils/terrain/__init__.py
forest_gen_utils/terrain/mesh.py
forest_gen_utils/terrain/terrain.py
forest_gen_utils/terrain/terrain_builder.py
forest_gen_utils/terrain/terrain_config.py
forest_gen_utils/terrain/terrain_generator.py
forest_gen_utils/terrain/microrelief/__init__.py
forest_gen_utils/terrain/microrelief/basic_microrelief.py
forest_gen_utils/terrain/microrelief/microrelief_strategy.py
forest_gen_utils/terrain/microrelief/none_microrelief.py
forest_gen_utils/terrain/moisture/__init__.py
forest_gen_utils/terrain/moisture/default_moisture_model.py
forest_gen_utils/terrain/moisture/moisture_model.py
forest_gen_utils/terrain/noise/__init__.py
forest_gen_utils/terrain/noise/fractal_noise.py
forest_gen_utils/terrain/noise/noise_factory.py
forest_gen_utils/terrain/noise/noise_strategy.py
forest_gen-0.3.8.dist-info/METADATA
forest_gen-0.3.8.dist-info/WHEEL
forest_gen-0.3.8.dist-info/top_level.txt
forest_gen-0.3.8.dist-info/RECORD
