Metadata-Version: 2.4
Name: forest_gen
Version: 0.3.8
Author-email: Tomasz Chady <tomek.chady@gmail.com>, Jakub Markil <jakub.markil1@gmail.com>, Patryk Olszewski <patryk.olszewski@vip.onet.pl>, Oskar Winiarski <oskarwiniarski09@gmail.com>
License-Expression: GPL-3.0-only
Project-URL: Repository, https://github.com/GrafCzterech/forest_gen
Requires-Python: >=3.10
License-File: LICENSE
Requires-Dist: numpy>=2.0.0
Requires-Dist: opensimplex==0.4.5.1
Requires-Dist: scipy>=1.0.0
Requires-Dist: stripe_kit
Requires-Dist: trimesh
Provides-Extra: dev
Requires-Dist: black; extra == "dev"
Requires-Dist: pytest; extra == "dev"
Provides-Extra: vis
Requires-Dist: matplotlib; extra == "vis"
Requires-Dist: ipykernel; extra == "vis"
Provides-Extra: export
Requires-Dist: pillow; extra == "export"
Dynamic: license-file
